fancyconfiglib/__init__.py
fancyconfiglib-1.2.dist-info/licenses/LICENSE
fancyconfiglib-1.2.dist-info/METADATA
fancyconfiglib-1.2.dist-info/WHEEL
fancyconfiglib-1.2.dist-info/top_level.txt
fancyconfiglib-1.2.dist-info/RECORD
