Metadata-Version: 2.4
Name: fancyconfiglib
Version: 1.2
Summary: A simple config library
Author-email: Patrick Karhoff <beepbooppk@gmail.com>
License: MIT License
Requires-Python: >=3.6
License-File: LICENSE
Dynamic: license-file
